{"nodes": [{"id": "home_leroy_project_sages_pi_yunxiao_scripts_test_e2e_sh", "label": "test-e2e.sh", "file_type": "code", "source_file": "pi-yunxiao/scripts/test-e2e.sh", "source_location": "L1", "metadata": {"language": "bash", "kind": "file"}}, {"id": "home_leroy_project_sages_pi_yunxiao_scripts_test_e2e_sh__entry", "label": "test-e2e.sh script", "file_type": "code", "source_file": "pi-yunxiao/scripts/test-e2e.sh", "source_location": "L1", "metadata": {"language": "bash", "kind": "bash_entrypoint"}}, {"id": "scripts_test_e2e_is_server_up", "label": "is_server_up()", "file_type": "code", "source_file": "pi-yunxiao/scripts/test-e2e.sh", "source_location": "L52", "metadata": {"language": "bash", "kind": "bash_function"}}], "edges": [{"source": "home_leroy_project_sages_pi_yunxiao_scripts_test_e2e_sh", "target": "home_leroy_project_sages_pi_yunxiao_scripts_test_e2e_sh__entry", "relation": "contains", "confidence": "EXTRACTED", "source_file": "pi-yunxiao/scripts/test-e2e.sh", "source_location": "L1", "weight": 1.0}, {"source": "home_leroy_project_sages_pi_yunxiao_scripts_test_e2e_sh", "target": "scripts_test_e2e_is_server_up", "relation": "defines", "confidence": "EXTRACTED", "source_file": "pi-yunxiao/scripts/test-e2e.sh", "source_location": "L52", "weight": 1.0}, {"source": "home_leroy_project_sages_pi_yunxiao_scripts_test_e2e_sh__entry", "target": "scripts_test_e2e_is_server_up", "relation": "calls", "confidence": "EXTRACTED", "source_file": "pi-yunxiao/scripts/test-e2e.sh", "source_location": "L61", "weight": 1.0, "context": "call"}]}